fastapi_localization/__init__.py
fastapi_localization/exception_handlers.py
fastapi_localization/localization.py
fastapi_localization/middleware.py
fastapi_localization/response.py
fastapi_localization/route.py
fastapi_localization-0.0a2.dev3.dist-info/LICENSE
fastapi_localization-0.0a2.dev3.dist-info/METADATA
fastapi_localization-0.0a2.dev3.dist-info/WHEEL
fastapi_localization-0.0a2.dev3.dist-info/top_level.txt
fastapi_localization-0.0a2.dev3.dist-info/RECORD
