Metadata-Version: 2.1
Name: fastapi-localization
Version: 0.0a2.dev3
Summary: Language localization fastapi
Home-page: https://github.com/ikasymov/fastapi-localization
Author: Ilgiz Kasymov
Author-email: ilgizkasymov@gmail.com
License: MIT
Platform: UNKNOWN
Requires-Python: >=3.7
Requires-Dist: fastapi
